{
  "minecraft:recipes/transportation/acacia_boat": {
    "criteria": {
      "in_water": "2022-03-13 23:09:23 -0500"
    },
    "done": true
  },
  "minecraft:recipes/transportation/oak_boat": {
    "criteria": {
      "in_water": "2022-03-13 23:09:23 -0500"
    },
    "done": true
  },
  "minecraft:recipes/transportation/dark_oak_boat": {
    "criteria": {
      "in_water": "2022-03-13 23:09:23 -0500"
    },
    "done": true
  },
  "minecraft:recipes/transportation/birch_boat": {
    "criteria": {
      "in_water": "2022-03-13 23:09:23 -0500"
    },
    "done": true
  },
  "minecraft:recipes/transportation/jungle_boat": {
    "criteria": {
      "in_water": "2022-03-13 23:09:23 -0500"
    },
    "done": true
  },
  "minecraft:recipes/transportation/spruce_boat": {
    "criteria": {
      "in_water": "2022-03-13 23:09:23 -0500"
    },
    "done": true
  },
  "minecraft:adventure/adventuring_time": {
    "criteria": {
      "minecraft:snowy_tundra": "2022-03-13 23:08:41 -0500"
    },
    "done": false
  },
  "DataVersion": 2730
}